RPackages/README.md
RPackages/__init__.py
RPackages/__main__.py
RPackages/file.epub
RPackages/index.html
RPackages/css/__init__.py
RPackages/css/annotations.css
RPackages/css/main.css
RPackages/css/normalize.css
RPackages/css/popup.css
RPackages/font/__init__.py
RPackages/font/fontello.eot
RPackages/font/fontello.svg
RPackages/font/fontello.ttf
RPackages/font/fontello.woff
RPackages/img/__init__.py
RPackages/img/annotator-glyph-sprite.png
RPackages/img/annotator-icon-sprite.png
RPackages/img/apple-touch-icon.png
RPackages/img/cancelfullscreen.png
RPackages/img/close.png
RPackages/img/fullscreen.png
RPackages/img/loader.gif
RPackages/img/menu-icon.png
RPackages/img/save.png
RPackages/img/saved.png
RPackages/img/settings-s.png
RPackages/img/settings.png
RPackages/img/star.png
RPackages/js/__init__.py
RPackages/js/epub.js
RPackages/js/epub.min.js
RPackages/js/epub.min.map
RPackages/js/hooks.min.js
RPackages/js/hooks.min.map
RPackages/js/reader.js
RPackages/js/reader.js.map
RPackages/js/reader.min.js
RPackages/js/reader.min.map
RPackages/js/hooks/__init__.py
RPackages/js/hooks/extensions/__init__.py
RPackages/js/hooks/extensions/highlight.js
RPackages/js/libs/__init__.py
RPackages/js/libs/jquery.min.js
RPackages/js/libs/localforage.min.js
RPackages/js/libs/screenfull.js
RPackages/js/libs/screenfull.min.js
RPackages/js/libs/zip.min.js
RPackages/js/plugins/__init__.py
RPackages/js/plugins/hypothesis.js
RPackages/js/plugins/search.js
r_packages-2024.3.4.0.dist-info/METADATA
r_packages-2024.3.4.0.dist-info/WHEEL
r_packages-2024.3.4.0.dist-info/entry_points.txt
r_packages-2024.3.4.0.dist-info/top_level.txt
r_packages-2024.3.4.0.dist-info/RECORD
